gs_tool/__init__.py
gs_tool/cli.py
gs_tool/config.py
gs_tool/project_template.json
gs_tool/bin/pawncc.exe
gs_tool/bin/include/AMXDLL.INC
gs_tool/bin/include/EPLAY.INC
gs_tool/bin/include/RND.INC
gs_tool/bin/include/args.inc
gs_tool/bin/include/bstring.inc
gs_tool/bin/include/console.inc
gs_tool/bin/include/core.inc
gs_tool/bin/include/datagram.inc
gs_tool/bin/include/default.inc
gs_tool/bin/include/file.inc
gs_tool/bin/include/fixed.inc
gs_tool/bin/include/float.inc
gs_tool/bin/include/power.inc
gs_tool/bin/include/process.inc
gs_tool/bin/include/rational.inc
gs_tool/bin/include/string.inc
gs_tool/bin/include/time.inc
gs_tool/templates/gs_natives.inc
gs_tool/templates/main.p.j2
gs_tool/templates/project.inc.j2
gs_tool-0.2.8.dist-info/METADATA
gs_tool-0.2.8.dist-info/WHEEL
gs_tool-0.2.8.dist-info/entry_points.txt
gs_tool-0.2.8.dist-info/top_level.txt
gs_tool-0.2.8.dist-info/RECORD
