Metadata-Version: 2.4
Name: gs-tool
Version: 0.2.8
Summary: A tool for managing telemetry scripts
Home-page: https://github.com/your-repo/gs_tool
Author: Konyaev Semyon
Author-email: s@7gis.ru
Classifier: Programming Language :: Python :: 3
Classifier: License :: OSI Approved :: MIT License
Classifier: Operating System :: OS Independent
Requires-Dist: click>=8.1.3
Requires-Dist: jinja2>=3.1.2
Requires-Dist: requests>=2.28.1
Dynamic: author
Dynamic: author-email
Dynamic: classifier
Dynamic: description
Dynamic: description-content-type
Dynamic: home-page
Dynamic: requires-dist
Dynamic: summary
